setup.py
bin/shaape
shaape/__init__.py
shaape/arrow.py
shaape/arrowparser.py
shaape/background.py
shaape/backgroundparser.py
shaape/cairobackend.py
shaape/cairoepsbackend.py
shaape/cairopdfbackend.py
shaape/cairosvgbackend.py
shaape/downarrow.py
shaape/drawable.py
shaape/drawingbackend.py
shaape/edge.py
shaape/font.py
shaape/graphalgorithms.py
shaape/leftarrow.py
shaape/named.py
shaape/nameparser.py
shaape/node.py
shaape/opengraph.py
shaape/optionparser.py
shaape/overlay.py
shaape/overlayparser.py
shaape/parser.py
shaape/polygon.py
shaape/rightarrow.py
shaape/rotatable.py
shaape/run.py
shaape/scalable.py
shaape/style.py
shaape/styleparser.py
shaape/text.py
shaape/textparser.py
shaape/translatable.py
shaape/uparrow.py
shaape/vector.py
shaape/yamlparser.py
shaape.egg-info/PKG-INFO
shaape.egg-info/SOURCES.txt
shaape.egg-info/dependency_links.txt
shaape.egg-info/requires.txt
shaape.egg-info/top_level.txt