Metadata-Version: 1.0
Name: shaape
Version: 1.1.1
Summary: Shaape - ascii art to image converter
Home-page: http://github.com/christiangoltz/shaape
Author: Christian Goltz
Author-email: goltzchristian@googlemail.com
License: LICENSE
Platform: UNKNOWN
